arkcserver-0.3.1.dist-info/metadata.json
arkcserver-0.3.1.dist-info/DESCRIPTION.rst
arkcserver-0.3.1.dist-info/entry_points.txt
arkcserver-0.3.1.dist-info/top_level.txt
arkcserver-0.3.1.dist-info/RECORD
arkcserver-0.3.1.dist-info/WHEEL
arkcserver-0.3.1.dist-info/METADATA
arkcserver/ptserver.py
arkcserver/client.py
arkcserver/meekserver.py
arkcserver/utils.py
arkcserver/main.py
arkcserver/proxy.py
arkcserver/coordinator.py
arkcserver/__init__.py
arkcserver/control.py
arkcserver/mailcheck/common.py
arkcserver/mailcheck/main.py
arkcserver/pyotp/totp.py
arkcserver/pyotp/utils.py
arkcserver/pyotp/otp.py
arkcserver/pyotp/__init__.py
arkcserver/twisted_connect_proxy/LICENSE
arkcserver/twisted_connect_proxy/server.py
arkcserver/twisted_connect_proxy/__init__.py
