Metadata-Version: 2.0
Name: arkcserver
Version: 0.3.1
Summary: A lightweight proxy designed to be proof to IP blocking measures
Home-page: https://arkc.org
Author: Noah, Teba, Ddeerreekk, Tsre
Author-email: noah@arkc.org
License: https://www.gnu.org/licenses/old-licenses/gpl-2.0.txt
Platform: UNKNOWN
Classifier: License :: OSI Approved :: GNU General Public License v2 or later (GPLv2+)
Classifier: Programming Language :: Python :: 2
Classifier: Programming Language :: Python :: 2 :: Only
Classifier: Programming Language :: Python :: 2.6
Classifier: Programming Language :: Python :: 2.7
Classifier: Programming Language :: Python :: Implementation :: CPython
Classifier: Topic :: Internet :: Proxy Servers
Requires-Dist: ntplib
Requires-Dist: twisted
Requires-Dist: pycrypto
Requires-Dist: txsocksx
Requires-Dist: dnslib
Requires-Dist: psutil
Requires-Dist: ipaddress
